[
  {
    "id": "f62514dc-171a-433d-80c5-e90e9a15f3b7",
    "data": [
      {
        "text": "Моя дочь поступила в другой город учиться",
        "userDefined": false
      }
    ],
    "isTemplate": false,
    "count": 0,
    "updated": 1541695378
  },
  {
    "id": "fba62cf6-ac41-4dd0-b712-ef008ed56548",
    "data": [
      {
        "text": "хочу съехать от родителей",
        "userDefined": false
      }
    ],
    "isTemplate": false,
    "count": 0,
    "updated": 1541695378
  },
  {
    "id": "94a52e96-7002-4884-992f-f386b309ee95",
    "data": [
      {
        "text": "хочу жить один",
        "userDefined": false
      }
    ],
    "isTemplate": false,
    "count": 0,
    "updated": 1541695378
  },
  {
    "id": "70eab59c-89e3-497f-8ee4-bfb6764660f2",
    "data": [
      {
        "text": " хочу жить одна",
        "userDefined": false
      }
    ],
    "isTemplate": false,
    "count": 0,
    "updated": 1541695378
  },
  {
    "id": "15df2a45-2eb7-4a9a-8853-fe100919717f",
    "data": [
      {
        "text": "Мой сын переехал в другой город учиться",
        "userDefined": false
      }
    ],
    "isTemplate": false,
    "count": 0,
    "updated": 1541695378
  },
  {
    "id": "d8cfe584-bb95-461d-8546-0ec07cfc9c52",
    "data": [
      {
        "text": "переехала в другой город",
        "userDefined": false
      }
    ],
    "isTemplate": false,
    "count": 0,
    "updated": 1541695378
  },
  {
    "id": "d35f304c-791f-42be-b7ff-84a47d18d9c6",
    "data": [
      {
        "text": "я переехала в другой город",
        "userDefined": false
      }
    ],
    "isTemplate": false,
    "count": 0,
    "updated": 1541695378
  }
]